rigid/__init__.py
rigid/api.py
rigid/deploy.py
rigid/file_scanner.py
rigid/utils.py
rigid/commands/__init__.py
rigid/commands/deploy.py
rigid-0.2.1.dist-info/DESCRIPTION.rst
rigid-0.2.1.dist-info/METADATA
rigid-0.2.1.dist-info/RECORD
rigid-0.2.1.dist-info/WHEEL
rigid-0.2.1.dist-info/entry_points.txt
rigid-0.2.1.dist-info/metadata.json
rigid-0.2.1.dist-info/top_level.txt
tests/__init__.py
tests/test_deploy.py
tests/test_file_scanner.py
tests/utils.py
tests/integration/__init__.py
tests/integration/test_app.py
tests/integration/test_apps.py
tests/integration/test_deploy.py
tests/integration/test_domains.py
tests/integration/test_login.py
tests/integration/test_promote.py
tests/integration/test_token.py
tests/integration/test_whoami.py
