Metadata-Version: 2.0
Name: rigid
Version: 0.2.1
Summary: Rig up your web application in seconds
Home-page: https://rigidapp.com/
Author: Kyle Fuller
Author-email: kyle@cocode.org
License: BSD
Platform: UNKNOWN
Classifier: Development Status :: 5 - Production/Stable
Classifier: Operating System :: OS Independent
Classifier: Programming Language :: Python :: 2
Classifier: Programming Language :: Python :: 2.7
Classifier: Programming Language :: Python :: 3
Classifier: Programming Language :: Python :: 3.5
Classifier: License :: OSI Approved :: BSD License
Requires-Dist: click
Requires-Dist: requests
Requires-Dist: pyyaml
